gitdraw/__init__.py
gitdraw/__main__.py
gitdraw/draw.py
gitdraw/parser.py
gitdraw/repo.py
gitdraw/svg_draw.py
gitdraw/templates/git_svg.j2
gitdraw-1.0.6.dist-info/LICENSE
gitdraw-1.0.6.dist-info/METADATA
gitdraw-1.0.6.dist-info/WHEEL
gitdraw-1.0.6.dist-info/entry_points.txt
gitdraw-1.0.6.dist-info/top_level.txt
gitdraw-1.0.6.dist-info/RECORD
