Metadata-Version: 2.1
Name: gitdraw
Version: 1.0.6
Summary: A simple tool for generating git graphs
Home-page: https://gitlab.com/broster/gitdraw
Author: Samuel Broster
Author-email: s.h.broster@gmail.com
License: MIT
Download-URL: https://gitlab.com/broster/gitdraw/-/archive/1.0.1/gitdraw-1.0.1.tar.gz
Keywords: git,graph,draw,svg
Platform: UNKNOWN
Classifier: Development Status :: 4 - Beta
Classifier: Intended Audience :: Developers
Classifier: Topic :: Software Development :: Build Tools
Classifier: License :: OSI Approved :: MIT License
Classifier: Programming Language :: Python :: 3.7
Requires-Dist: jinja2
Requires-Dist: parsimonious
Requires-Dist: palettable
